<?xml version="1.0" encoding="UTF-8" standalone="no"?>
<query xmlns:yahoo="http://www.yahooapis.com/v1/base.rng" yahoo:count="3" yahoo:created="2018-11-24T12:25:36Z" yahoo:lang="en-US">
  <results>
    <channel>
      <yweather:units xmlns:yweather="http://xml.weather.yahoo.com/ns/rss/1.0" distance="km" pressure="mb" speed="km/h" temperature="C"/>
      <title>Yahoo! Weather - Stuttgart, BW, DE</title>
      <link>http://us.rd.yahoo.com/dailynews/rss/weather/Country__Country/*https://weather.yahoo.com/country/state/city-698064/</link>
      <description>Yahoo! Weather for Stuttgart, BW, DE</description>
      <language>en-us</language>
      <lastBuildDate>Sat, 24 Nov 2018 01:25 PM CET</lastBuildDate>
      <ttl>60</ttl>
      <yweather:location xmlns:yweather="http://xml.weather.yahoo.com/ns/rss/1.0" city="Stuttgart" country="Germany" region=" BW"/>
      <yweather:wind xmlns:yweather="http://xml.weather.yahoo.com/ns/rss/1.0" chill="46" direction="235" speed="25.75"/>
      <yweather:atmosphere xmlns:yweather="http://xml.weather.yahoo.com/ns/rss/1.0" humidity="76" pressure="32847.98" rising="0" visibility="25.91"/>
      <yweather:astronomy xmlns:yweather="http://xml.weather.yahoo.com/ns/rss/1.0" sunrise="7:46 am" sunset="4:34 pm"/>
      <image>
        <title>Yahoo! Weather</title>
        <width>142</width>
        <height>18</height>
        <link>http://weather.yahoo.com</link>
        <url>http://l.yimg.com/a/i/brand/purplelogo//uh/us/news-wea.gif</url>
      </image>
      <item>
        <title>Conditions for Stuttgart, BW, DE at 12:00 PM CET</title>
        <geo:lat xmlns:geo="http://www.w3.org/2003/01/geo/wgs84_pos#">48.76767</geo:lat>
        <geo:long xmlns:geo="http://www.w3.org/2003/01/geo/wgs84_pos#">9.17192</geo:long>
        <link>http://us.rd.yahoo.com/dailynews/rss/weather/Country__Country/*https://weather.yahoo.com/country/state/city-698064/</link>
        <pubDate>Sat, 24 Nov 2018 12:00 PM CET</pubDate>
        <yweather:condition xmlns:yweather="http://xml.weather.yahoo.com/ns/rss/1.0" code="30" date="Sat, 24 Nov 2018 12:00 PM CET" temp="10" text="Partly Cloudy"/>
        <yweather:forecast xmlns:yweather="http://xml.weather.yahoo.com/ns/rss/1.0" code="5" date="24 Nov 2018" day="Sat" high="8" low="2" text="Rain And Snow"/>
        <yweather:forecast xmlns:yweather="http://xml.weather.yahoo.com/ns/rss/1.0" code="30" date="25 Nov 2018" day="Sun" high="5" low="-1" text="Partly Cloudy"/>
        <yweather:forecast xmlns:yweather="http://xml.weather.yahoo.com/ns/rss/1.0" code="5" date="26 Nov 2018" day="Mon" high="2" low="1" text="Rain And Snow"/>
        <yweather:forecast xmlns:yweather="http://xml.weather.yahoo.com/ns/rss/1.0" code="5" date="27 Nov 2018" day="Tue" high="1" low="0" text="Rain And Snow"/>
        <yweather:forecast xmlns:yweather="http://xml.weather.yahoo.com/ns/rss/1.0" code="28" date="28 Nov 2018" day="Wed" high="1" low="-1" text="Mostly Cloudy"/>
        <yweather:forecast xmlns:yweather="http://xml.weather.yahoo.com/ns/rss/1.0" code="39" date="29 Nov 2018" day="Thu" high="6" low="0" text="Scattered Showers"/>
        <yweather:forecast xmlns:yweather="http://xml.weather.yahoo.com/ns/rss/1.0" code="39" date="30 Nov 2018" day="Fri" high="7" low="3" text="Scattered Showers"/>
        <yweather:forecast xmlns:yweather="http://xml.weather.yahoo.com/ns/rss/1.0" code="39" date="01 Dec 2018" day="Sat" high="6" low="4" text="Scattered Showers"/>
        <yweather:forecast xmlns:yweather="http://xml.weather.yahoo.com/ns/rss/1.0" code="39" date="02 Dec 2018" day="Sun" high="8" low="4" text="Scattered Showers"/>
        <yweather:forecast xmlns:yweather="http://xml.weather.yahoo.com/ns/rss/1.0" code="39" date="03 Dec 2018" day="Mon" high="9" low="5" text="Scattered Showers"/>
        <description>&lt;![CDATA[&lt;img src="http://l.yimg.com/a/i/us/we/52/30.gif"/&gt;
&lt;BR /&gt;
&lt;b&gt;Current Conditions:&lt;/b&gt;
&lt;BR /&gt;Partly Cloudy
&lt;BR /&gt;
&lt;BR /&gt;
&lt;b&gt;Forecast:&lt;/b&gt;
&lt;BR /&gt; Sat - Rain And Snow. High: 8Low: 2
&lt;BR /&gt; Sun - Partly Cloudy. High: 5Low: -1
&lt;BR /&gt; Mon - Rain And Snow. High: 2Low: 1
&lt;BR /&gt; Tue - Rain And Snow. High: 1Low: 0
&lt;BR /&gt; Wed - Mostly Cloudy. High: 1Low: -1
&lt;BR /&gt;
&lt;BR /&gt;
&lt;a href="http://us.rd.yahoo.com/dailynews/rss/weather/Country__Country/*https://weather.yahoo.com/country/state/city-698064/"&gt;Full Forecast at Yahoo! Weather&lt;/a&gt;
&lt;BR /&gt;
&lt;BR /&gt;
&lt;BR /&gt;
]]&gt;</description>
        <guid isPermaLink="false"/>
      </item>
    </channel>
    <channel>
      <yweather:units xmlns:yweather="http://xml.weather.yahoo.com/ns/rss/1.0" distance="km" pressure="mb" speed="km/h" temperature="C"/>
      <title>Yahoo! Weather - Stuttgart, AR, US</title>
      <link>http://us.rd.yahoo.com/dailynews/rss/weather/Country__Country/*https://weather.yahoo.com/country/state/city-2501152/</link>
      <description>Yahoo! Weather for Stuttgart, AR, US</description>
      <language>en-us</language>
      <lastBuildDate>Sat, 24 Nov 2018 06:25 AM CST</lastBuildDate>
      <ttl>60</ttl>
      <yweather:location xmlns:yweather="http://xml.weather.yahoo.com/ns/rss/1.0" city="Stuttgart" country="United States" region=" AR"/>
      <yweather:wind xmlns:yweather="http://xml.weather.yahoo.com/ns/rss/1.0" chill="48" direction="245" speed="11.27"/>
      <yweather:atmosphere xmlns:yweather="http://xml.weather.yahoo.com/ns/rss/1.0" humidity="96" pressure="33897.76" rising="0" visibility="15.13"/>
      <yweather:astronomy xmlns:yweather="http://xml.weather.yahoo.com/ns/rss/1.0" sunrise="6:48 am" sunset="4:57 pm"/>
      <image>
        <title>Yahoo! Weather</title>
        <width>142</width>
        <height>18</height>
        <link>http://weather.yahoo.com</link>
        <url>http://l.yimg.com/a/i/brand/purplelogo//uh/us/news-wea.gif</url>
      </image>
      <item>
        <title>Conditions for Stuttgart, AR, US at 05:00 AM CST</title>
        <geo:lat xmlns:geo="http://www.w3.org/2003/01/geo/wgs84_pos#">34.4939</geo:lat>
        <geo:long xmlns:geo="http://www.w3.org/2003/01/geo/wgs84_pos#">-91.547791</geo:long>
        <link>http://us.rd.yahoo.com/dailynews/rss/weather/Country__Country/*https://weather.yahoo.com/country/state/city-2501152/</link>
        <pubDate>Sat, 24 Nov 2018 05:00 AM CST</pubDate>
        <yweather:condition xmlns:yweather="http://xml.weather.yahoo.com/ns/rss/1.0" code="31" date="Sat, 24 Nov 2018 05:00 AM CST" temp="9" text="Clear"/>
        <yweather:forecast xmlns:yweather="http://xml.weather.yahoo.com/ns/rss/1.0" code="30" date="24 Nov 2018" day="Sat" high="17" low="8" text="Partly Cloudy"/>
        <yweather:forecast xmlns:yweather="http://xml.weather.yahoo.com/ns/rss/1.0" code="28" date="25 Nov 2018" day="Sun" high="16" low="4" text="Mostly Cloudy"/>
        <yweather:forecast xmlns:yweather="http://xml.weather.yahoo.com/ns/rss/1.0" code="34" date="26 Nov 2018" day="Mon" high="7" low="0" text="Mostly Sunny"/>
        <yweather:forecast xmlns:yweather="http://xml.weather.yahoo.com/ns/rss/1.0" code="34" date="27 Nov 2018" day="Tue" high="10" low="-1" text="Mostly Sunny"/>
        <yweather:forecast xmlns:yweather="http://xml.weather.yahoo.com/ns/rss/1.0" code="34" date="28 Nov 2018" day="Wed" high="10" low="0" text="Mostly Sunny"/>
        <yweather:forecast xmlns:yweather="http://xml.weather.yahoo.com/ns/rss/1.0" code="28" date="29 Nov 2018" day="Thu" high="11" low="2" text="Mostly Cloudy"/>
        <yweather:forecast xmlns:yweather="http://xml.weather.yahoo.com/ns/rss/1.0" code="39" date="30 Nov 2018" day="Fri" high="15" low="8" text="Scattered Showers"/>
        <yweather:forecast xmlns:yweather="http://xml.weather.yahoo.com/ns/rss/1.0" code="39" date="01 Dec 2018" day="Sat" high="17" low="10" text="Scattered Showers"/>
        <yweather:forecast xmlns:yweather="http://xml.weather.yahoo.com/ns/rss/1.0" code="30" date="02 Dec 2018" day="Sun" high="13" low="8" text="Partly Cloudy"/>
        <yweather:forecast xmlns:yweather="http://xml.weather.yahoo.com/ns/rss/1.0" code="39" date="03 Dec 2018" day="Mon" high="11" low="7" text="Scattered Showers"/>
        <description>&lt;![CDATA[&lt;img src="http://l.yimg.com/a/i/us/we/52/31.gif"/&gt;
&lt;BR /&gt;
&lt;b&gt;Current Conditions:&lt;/b&gt;
&lt;BR /&gt;Clear
&lt;BR /&gt;
&lt;BR /&gt;
&lt;b&gt;Forecast:&lt;/b&gt;
&lt;BR /&gt; Sat - Partly Cloudy. High: 17Low: 8
&lt;BR /&gt; Sun - Mostly Cloudy. High: 16Low: 4
&lt;BR /&gt; Mon - Mostly Sunny. High: 7Low: 0
&lt;BR /&gt; Tue - Mostly Sunny. High: 10Low: -1
&lt;BR /&gt; Wed - Mostly Sunny. High: 10Low: 0
&lt;BR /&gt;
&lt;BR /&gt;
&lt;a href="http://us.rd.yahoo.com/dailynews/rss/weather/Country__Country/*https://weather.yahoo.com/country/state/city-2501152/"&gt;Full Forecast at Yahoo! Weather&lt;/a&gt;
&lt;BR /&gt;
&lt;BR /&gt;
&lt;BR /&gt;
]]&gt;</description>
        <guid isPermaLink="false"/>
      </item>
    </channel>
    <channel>
      <yweather:units xmlns:yweather="http://xml.weather.yahoo.com/ns/rss/1.0" distance="km" pressure="mb" speed="km/h" temperature="C"/>
      <title>Yahoo! Weather - Stuttgart, KS, US</title>
      <link>http://us.rd.yahoo.com/dailynews/rss/weather/Country__Country/*https://weather.yahoo.com/country/state/city-2501151/</link>
      <description>Yahoo! Weather for Stuttgart, KS, US</description>
      <language>en-us</language>
      <lastBuildDate>Sat, 24 Nov 2018 06:25 AM CST</lastBuildDate>
      <ttl>60</ttl>
      <yweather:location xmlns:yweather="http://xml.weather.yahoo.com/ns/rss/1.0" city="Stuttgart" country="United States" region=" KS"/>
      <yweather:wind xmlns:yweather="http://xml.weather.yahoo.com/ns/rss/1.0" chill="28" direction="330" speed="17.70"/>
      <yweather:atmosphere xmlns:yweather="http://xml.weather.yahoo.com/ns/rss/1.0" humidity="74" pressure="31730.47" rising="0" visibility="25.91"/>
      <yweather:astronomy xmlns:yweather="http://xml.weather.yahoo.com/ns/rss/1.0" sunrise="7:32 am" sunset="5:16 pm"/>
      <image>
        <title>Yahoo! Weather</title>
        <width>142</width>
        <height>18</height>
        <link>http://weather.yahoo.com</link>
        <url>http://l.yimg.com/a/i/brand/purplelogo//uh/us/news-wea.gif</url>
      </image>
      <item>
        <title>Conditions for Stuttgart, KS, US at 05:00 AM CST</title>
        <geo:lat xmlns:geo="http://www.w3.org/2003/01/geo/wgs84_pos#">39.797798</geo:lat>
        <geo:long xmlns:geo="http://www.w3.org/2003/01/geo/wgs84_pos#">-99.451797</geo:long>
        <link>http://us.rd.yahoo.com/dailynews/rss/weather/Country__Country/*https://weather.yahoo.com/country/state/city-2501151/</link>
        <pubDate>Sat, 24 Nov 2018 05:00 AM CST</pubDate>
        <yweather:condition xmlns:yweather="http://xml.weather.yahoo.com/ns/rss/1.0" code="31" date="Sat, 24 Nov 2018 05:00 AM CST" temp="1" text="Clear"/>
        <yweather:forecast xmlns:yweather="http://xml.weather.yahoo.com/ns/rss/1.0" code="30" date="24 Nov 2018" day="Sat" high="15" low="-1" text="Partly Cloudy"/>
        <yweather:forecast xmlns:yweather="http://xml.weather.yahoo.com/ns/rss/1.0" code="5" date="25 Nov 2018" day="Sun" high="3" low="-3" text="Rain And Snow"/>
        <yweather:forecast xmlns:yweather="http://xml.weather.yahoo.com/ns/rss/1.0" code="34" date="26 Nov 2018" day="Mon" high="7" low="-5" text="Mostly Sunny"/>
        <yweather:forecast xmlns:yweather="http://xml.weather.yahoo.com/ns/rss/1.0" code="34" date="27 Nov 2018" day="Tue" high="7" low="-5" text="Mostly Sunny"/>
        <yweather:forecast xmlns:yweather="http://xml.weather.yahoo.com/ns/rss/1.0" code="28" date="28 Nov 2018" day="Wed" high="7" low="-3" text="Mostly Cloudy"/>
        <yweather:forecast xmlns:yweather="http://xml.weather.yahoo.com/ns/rss/1.0" code="28" date="29 Nov 2018" day="Thu" high="8" low="-3" text="Mostly Cloudy"/>
        <yweather:forecast xmlns:yweather="http://xml.weather.yahoo.com/ns/rss/1.0" code="39" date="30 Nov 2018" day="Fri" high="8" low="-3" text="Scattered Showers"/>
        <yweather:forecast xmlns:yweather="http://xml.weather.yahoo.com/ns/rss/1.0" code="47" date="01 Dec 2018" day="Sat" high="10" low="0" text="Scattered Thunderstorms"/>
        <yweather:forecast xmlns:yweather="http://xml.weather.yahoo.com/ns/rss/1.0" code="30" date="02 Dec 2018" day="Sun" high="7" low="-3" text="Partly Cloudy"/>
        <yweather:forecast xmlns:yweather="http://xml.weather.yahoo.com/ns/rss/1.0" code="30" date="03 Dec 2018" day="Mon" high="3" low="-5" text="Partly Cloudy"/>
        <description>&lt;![CDATA[&lt;img src="http://l.yimg.com/a/i/us/we/52/31.gif"/&gt;
&lt;BR /&gt;
&lt;b&gt;Current Conditions:&lt;/b&gt;
&lt;BR /&gt;Clear
&lt;BR /&gt;
&lt;BR /&gt;
&lt;b&gt;Forecast:&lt;/b&gt;
&lt;BR /&gt; Sat - Partly Cloudy. High: 15Low: -1
&lt;BR /&gt; Sun - Rain And Snow. High: 3Low: -3
&lt;BR /&gt; Mon - Mostly Sunny. High: 7Low: -5
&lt;BR /&gt; Tue - Mostly Sunny. High: 7Low: -5
&lt;BR /&gt; Wed - Mostly Cloudy. High: 7Low: -3
&lt;BR /&gt;
&lt;BR /&gt;
&lt;a href="http://us.rd.yahoo.com/dailynews/rss/weather/Country__Country/*https://weather.yahoo.com/country/state/city-2501151/"&gt;Full Forecast at Yahoo! Weather&lt;/a&gt;
&lt;BR /&gt;
&lt;BR /&gt;
&lt;BR /&gt;
]]&gt;</description>
        <guid isPermaLink="false"/>
      </item>
    </channel>
  </results>
</query><!-- total: 11 -->
